jsonkv/__init__.py
jsonkv/filelock.py
jsonkv/kv.py
jsonkv-1.1.10.dist-info/METADATA
jsonkv-1.1.10.dist-info/WHEEL
jsonkv-1.1.10.dist-info/top_level.txt
jsonkv-1.1.10.dist-info/RECORD
